{
  "id": "QuizLab",
  "realm": "QuizLab",
  "enabled": true,
  "registrationAllowed": true,
  "loginTheme": "quizlab",
  "users": [
    {
      "username": "studente1",
      "enabled": true,
      "email": "studente1@techmatrix.it",
      "firstName": "Studente",
      "lastName": "Uno",
      "credentials": [
        {
          "type": "password",
          "value": "studente1",
          "temporary": false
        }
      ]
    }
  ],
  "clients": [
    {
      "clientId": "oauth2-proxy-client",
      "name": "OAuth2 Proxy Client",
      "enabled": true,
      "secret": "${env.OAUTH2_PROXY_CLIENT_SECRET}",
      "protocol": "openid-connect",
      "publicClient": false,
      "standardFlowEnabled": true,
      "directAccessGrantsEnabled": true,
      "redirectUris": [
        "*"
      ],
      "webOrigins": [
        "*"
      ],
      "defaultClientScopes": [
        "web-origins",
        "acr",
        "roles",
        "profile",
        "email"
      ]
    }
  ]
}
